UVTextureConverter/Atlas2Normal.py
UVTextureConverter/Normal2Atlas.py
UVTextureConverter/UVConverter.py
UVTextureConverter/__init__.py
UVTextureConverter/config/UV_Processed.mat
UVTextureConverter/config/normal.pickle
UVTextureConverter/config/normal_faces.pickle
UVTextureConverter/mapping_relations/atlas2normal_200_512.pickle
UVTextureConverter/mapping_relations/normal2atlas_512_200.pickle
uvtextureconverter-1.2.0.dist-info/LICENSE
uvtextureconverter-1.2.0.dist-info/WHEEL
uvtextureconverter-1.2.0.dist-info/METADATA
uvtextureconverter-1.2.0.dist-info/RECORD
