Metadata-Version: 2.1
Name: uvtextureconverter
Version: 1.2.0
Summary: To convert atlas texuture (defined in Densepose) to normal texture (defined in SMPL), and vice versa.
Home-page: https://github.com/kuboshizuma/UVTextureConverter
Author: Shizuma Kubo
Requires-Python: >=3.6,<4.0
Classifier: Programming Language :: Python :: 3
Classifier: Programming Language :: Python :: 3.6
Classifier: Programming Language :: Python :: 3.7
Classifier: Programming Language :: Python :: 3.8
Classifier: Programming Language :: Python :: 3.9
Requires-Dist: numpy
Requires-Dist: scipy
Requires-Dist: tqdm
Project-URL: Repository, https://github.com/kuboshizuma/UVTextureConverter
